outray/__init__.py
outray/exceptions.py
outray/helpers.py
outray/http_client.py
outray/messages.py
outray/outray.py
outray/listeners/__init__.py
outray/listeners/http.py
outray/listeners/tcp.py
outray/listeners/udp.py
outray-0.0.3.dist-info/METADATA
outray-0.0.3.dist-info/WHEEL
outray-0.0.3.dist-info/licenses/LICENSE
outray-0.0.3.dist-info/RECORD
