Metadata-Version: 2.4
Name: outray
Version: 0.0.3
Summary: Python SDK for outray.dev tunneling service
Project-URL: Homepage, https://github.com/Eghosa-Osayande/outray-python
Project-URL: Issues, https://github.com/Eghosa-Osayande/outray-python/issues
Author-email: Eghosa Osayande <osayandeeghosam@gmail.com>
License-Expression: MIT
License-File: LICENSE
Classifier: License :: OSI Approved :: MIT License
Classifier: Programming Language :: Python
Classifier: Programming Language :: Python :: 3
Requires-Python: >=3.10
Requires-Dist: dotenv
Requires-Dist: websockets
